dicom_tools/BrukerMRI.py
dicom_tools/DynamicArray.py
dicom_tools/FileReader.py
dicom_tools/MyStatusBar.py
dicom_tools/Normalizer.py
dicom_tools/__init__.py
dicom_tools/anonymize.py
dicom_tools/calculateMeanInROI.py
dicom_tools/check_dir.py
dicom_tools/colorize.py
dicom_tools/connectedThreshold.py
dicom_tools/convertTypes.py
dicom_tools/curvatureFlowImageFilter.py
dicom_tools/fractal.py
dicom_tools/gaussianlaplace.py
dicom_tools/getEntropy.py
dicom_tools/getLayerWithLargerROI.py
dicom_tools/highlight_color.py
dicom_tools/highlightroi.py
dicom_tools/histFromArray.py
dicom_tools/ifNeededMkdir.py
dicom_tools/info_file_parser.py
dicom_tools/intensity_cut.py
dicom_tools/make_histo.py
dicom_tools/make_histo_entropy.py
dicom_tools/make_histo_ofallpixels.py
dicom_tools/morphologicalWatershed.py
dicom_tools/myroi2roi.py
dicom_tools/newNameFromMetadata.py
dicom_tools/nrrdFileHandler.py
dicom_tools/osirix_roi_to_numpy.py
dicom_tools/read_files.py
dicom_tools/read_plist_roi_file.py
dicom_tools/rescale.py
dicom_tools/roi2myroi.py
dicom_tools/roiData.py
dicom_tools/roiFileHandler.py
dicom_tools/show.py
dicom_tools/sitk_show.py
dicom_tools/splitWithEscapes.py
dicom_tools/timeflagconverter.py
dicom_tools/wardHierarchical.py
dicom_tools/xlsReader.py
dicom_tools/pyqtgraph/PlotData.py
dicom_tools/pyqtgraph/Point.py
dicom_tools/pyqtgraph/Qt.py
dicom_tools/pyqtgraph/SRTTransform.py
dicom_tools/pyqtgraph/SRTTransform3D.py
dicom_tools/pyqtgraph/SignalProxy.py
dicom_tools/pyqtgraph/ThreadsafeTimer.py
dicom_tools/pyqtgraph/Transform3D.py
dicom_tools/pyqtgraph/Vector.py
dicom_tools/pyqtgraph/WidgetGroup.py
dicom_tools/pyqtgraph/__init__.py
dicom_tools/pyqtgraph/colormap.py
dicom_tools/pyqtgraph/configfile.py
dicom_tools/pyqtgraph/debug.py
dicom_tools/pyqtgraph/exceptionHandling.py
dicom_tools/pyqtgraph/frozenSupport.py
dicom_tools/pyqtgraph/functions.py
dicom_tools/pyqtgraph/graphicsWindows.py
dicom_tools/pyqtgraph/numpy_fix.py
dicom_tools-2.2.dist-info/METADATA
dicom_tools-2.2.dist-info/RECORD
dicom_tools-2.2.dist-info/WHEEL
dicom_tools-2.2.dist-info/top_level.txt
