Metadata-Version: 2.1
Name: dicom-tools
Version: 2.2
Summary: Package for DICOM medical images analysis.
Home-page: http://www.roma1.infn.it/~mancinit/Software/dicom_tools
Author: Carlo Mancini Terracciano
Author-email: carlo.mancini.terracciano@roma1.infn.it
License: MIT
Download-URL: https://github.com/carlomt/dicom_tools/archive/1.0.tar.gz
Keywords: medical,image-analysis
Platform: UNKNOWN
Classifier: Programming Language :: Python :: 3
Classifier: License :: OSI Approved :: MIT License
Classifier: Operating System :: OS Independent
Requires-Dist: scipy (>=0.17.1)
Requires-Dist: numpy (>=1.10.0)
Requires-Dist: pydicom (>=0.9.9)
Requires-Dist: pynrrd (>=0.2.1)
Requires-Dist: scikit-image (>=0.12.3)
Requires-Dist: scikit-learn (>=0.18)
Requires-Dist: nose (>=1.3.7)
Requires-Dist: SimpleITK (>=0.10.0)
Requires-Dist: tabulate (>=0.7.7)
Requires-Dist: openpyxl (>=2.4.0)
Requires-Dist: ipython (<6)
Requires-Dist: qtconsole
